Metadata-Version: 2.1
Name: re-int-ineq
Version: 0.9.0
Summary: Generate regular expressions to match integers greater than / less than / etc. a value
Author-email: Hauke D <haukex@zero-g.net>
Project-URL: Homepage, https://github.com/haukex/re-int-ineq
Project-URL: Bug Tracker, https://github.com/haukex/re-int-ineq/issues
Classifier: Programming Language :: Python :: 3
Classifier: Programming Language :: Python :: 3.9
Classifier: Programming Language :: Python :: 3.10
Classifier: Programming Language :: Python :: 3.11
Classifier: Programming Language :: Python :: 3.12
Classifier: Programming Language :: Python :: 3.13
Classifier: License :: OSI Approved :: GNU Lesser General Public License v3 or later (LGPLv3+)
Classifier: Development Status :: 4 - Beta
Classifier: Topic :: Software Development :: Libraries
Classifier: Topic :: Software Development :: Code Generators
Requires-Python: >=3.9
License-File: LICENSE.txt
